Metadata-Version: 2.1
Name: ThiccStatus
Version: 1.0.0
Summary: Discord module for ThiccStatus.
Home-page: https://isthicc.dev/
Author: IsThicc Software
License: UNKNOWN
Platform: UNKNOWN
